Workbook
Name Slicer_Age_Group: #N/A
Name Slicer_Age_Group1: #N/A
Name Slicer_Category: #N/A
Name Slicer_Category1: #N/A
Name Slicer_Channel: #N/A
Name Slicer_Channel1: #N/A
Name Slicer_City: #N/A
Name Slicer_Gender: #N/A
Name Slicer_Gender1: #N/A

Sheet Row Data
A1: Order ID | B1: Date | C1: City | D1: Category | E1: Product | F1: Age | G1: Gender | H1: Sales | I1: Quantity | J1: Channel | K1: Payment Mode | L1: Rating
A2: 1001 | B2: 45658 | C2: Bengaluru | D2: Skincare | E2: Face Serum | F2: 24 | G2: Female | H2: 1200 | I2: 2 | J2: Online | K2: UPI | L2: 4.5
A3: 1002 | B3: 45660 | C3: Mumbai | D3: Haircare | E3: Shampoo | F3: 31 | G3: Female | H3: 850 | I3: 1 | J3: Retail Store | K3: Card | L3: 4
A4: 1003 | B4: 45662 | C4: Delhi | D4: Makeup | E4: Lipstick | F4: 27 | G4: Female | H4: 1500 | I4: 3 | J4: Online | K4: UPI | L4: 4.7
A5: 1004 | B5: 45665 | C5: Bengaluru | D5: Wellness | E5: Vitamin Pack | F5: 35 | G5: Male | H5: 2200 | I5: 2 | J5: Retail Store | K5: Card | L5: 4.2
A6: 1005 | B6: 45669 | C6: Pune | D6: Fragrance | E6: Perfume | F6: 29 | G6: Female | H6: 1800 | I6: 1 | J6: Online | K6: Wallet | L6: 4.8
A7: 1006 | B7: 45672 | C7: Chennai | D7: Skincare | E7: Face Wash | F7: 22 | G7: Female | H7: 650 | I7: 2 | J7: Online | K7: UPI | L7: 4.1
A8: 1007 | B8: 45675 | C8: Hyderabad | D8: Haircare | E8: Hair Oil | F8: 40 | G8: Male | H8: 900 | I8: 2 | J8: Retail Store | K8: Cash | L8: 3.9
A9: 1008 | B9: 45679 | C9: Bengaluru | D9: Makeup | E9: Foundation | F9: 26 | G9: Female | H9: 2100 | I9: 2 | J9: Online | K9: Card | L9: 4.6
A10: 1009 | B10: 45682 | C10: Mumbai | D10: Wellness | E10: Protein Powder | F10: 33 | G10: Male | H10: 2500 | I10: 1 | J10: Online | K10: UPI | L10: 4.4
A11: 1010 | B11: 45685 | C11: Delhi | D11: Skincare | E11: Moisturizer | F11: 37 | G11: Female | H11: 1100 | I11: 2 | J11: Retail Store | K11: Card | L11: 4.3
A12: 1011 | B12: 45690 | C12: Bengaluru | D12: Skincare | E12: Face Serum | F12: 25 | G12: Female | H12: 2400 | I12: 3 | J12: Online | K12: UPI | L12: 4.9
A13: 1012 | B13: 45693 | C13: Mumbai | D13: Haircare | E13: Shampoo | F13: 30 | G13: Female | H13: 1300 | I13: 2 | J13: Retail Store | K13: Card | L13: 4.1
... A121: 1120 | B121: 46016 | C121: Delhi | D121: Skincare | E121: Moisturizer | F121: 36 | G121: Female | H121: 2000 | I121: 2 | J121: Retail Store | K121: Card | L121: 4.8

Sheet Product Analysis
A3: Row Labels | B3: Sum of Sales
A4: Vitamin Pack | B4: 38250
A5: Face Serum | B5: 33300
A6: Foundation | B6: 32400
A7: Grand Total | B7: 103950
A20: Row Labels | B20: Sum of Sales
A21: Foundation | B21: 32400
A22: Face Serum | B22: 33300
A23: Vitamin Pack | B23: 38250
A24: Grand Total | B24: 103950

Sheet Rating Analysis
A3: Row Labels | B3: Count of Order IDA1:J21
A4: 4.2 | B4: 1
A5: 4.3 | B5: 1
A6: 4.5 | B6: 3
A7: 4.6 | B7: 5
A8: 4.7 | B8: 5
A9: 4.8 | B9: 4
A10: 4.9 | B10: 13
A11: 5 | B11: 4
A12: Grand Total | B12: 36
A21: Row Labels | B21: Sum of Sales | C21: Count of Order IDA1:J21 | D21: Sum of Quantity
A22: Online | B22: 101750 | C22: 35 | D22: 79
A23: Retail Store | B23: 2200 | C23: 1 | D23: 2
A24: Grand Total | B24: 103950 | C24: 36 | D24: 81
C37: City Performance
A38: Row Labels | B38: Sum of Sales | C38: Count of Order IDA1:J21
A39: Bengaluru | B39: 103950 | C39: 36
A40: Grand Total | B40: 103950 | C40: 36
B56: Monthly Sales Performance
A57: Row Labels | B57: Sum of Sales
A58: Jan | B58: 5500
A59: Feb | B59: 7500
A60: Mar | B60: 6250
A61: Apr | B61: 7900
A62: May | B62: 8500
A63: Jun | B63: 7200
A64: Jul | B64: 9050
A65: Aug | B65: 9250
A66: Sep | B66: 9850
A67: Oct | B67: 10350
A68: Nov | B68: 10950
A69: Dec | B69: 11650
A70: Grand Total | B70: 103950

Sheet Cleaned Data
A1: Order ID | B1: Date | C1: City | D1: Category | E1: Product | F1: Age | G1: Gender | H1: Sales | I1: Quantity | J1: Channel | K1: Payment Mode | L1: Rating | M1: Age Group
A2: 1115 | B2: 46001 | C2: Pune | D2: Fragrance | E2: Perfume | F2: 36 | G2: Female | H2: 6000 | I2: 3 | J2: Online | K2: Wallet | L2: 5 | M2: =IF(F2<25,"18-24",IF(F2<35,"25-34",IF(F2<45,"35-44","45+"))) -> 35-44
A3: 1105 | B3: 45971 | C3: Pune | D3: Fragrance | E3: Perfume | F3: 35 | G3: Female | H3: 5500 | I3: 3 | J3: Online | K3: Wallet | L3: 5 | M3: =IF(F3<25,"18-24",IF(F3<35,"25-34",IF(F3<45,"35-44","45+"))) -> 35-44
A4: 1095 | B4: 45940 | C4: Pune | D4: Fragrance | E4: Perfume | F4: 31 | G4: Female | H4: 5200 | I4: 3 | J4: Online | K4: Wallet | L4: 5 | M4: =IF(F4<25,"18-24",IF(F4<35,"25-34",IF(F4<45,"35-44","45+"))) -> 25-34
A5: 1085 | B5: 45910 | C5: Pune | D5: Fragrance | E5: Perfume | F5: 29 | G5: Female | H5: 4700 | I5: 3 | J5: Online | K5: Wallet | L5: 5 | M5: =IF(F5<25,"18-24",IF(F5<35,"25-34",IF(F5<45,"35-44","45+"))) -> 25-34
A6: 1075 | B6: 45878 | C6: Pune | D6: Fragrance | E6: Perfume | F6: 33 | G6: Female | H6: 4500 | I6: 3 | J6: Online | K6: Wallet | L6: 5 | M6: =IF(F6<25,"18-24",IF(F6<35,"25-34",IF(F6<45,"35-44","45+"))) -> 25-34
A7: 1119 | B7: 46013 | C7: Mumbai | D7: Wellness | E7: Protein Powder | F7: 38 | G7: Male | H7: 4500 | I7: 2 | J7: Online | K7: UPI | L7: 4.9 | M7: =IF(F7<25,"18-24",IF(F7<35,"25-34",IF(F7<45,"35-44","45+"))) -> 35-44
A8: 1109 | B8: 45983 | C8: Mumbai | D8: Wellness | E8: Protein Powder | F8: 37 | G8: Male | H8: 4300 | I8: 2 | J8: Online | K8: UPI | L8: 4.9 | M8: =IF(F8<25,"18-24",IF(F8<35,"25-34",IF(F8<45,"35-44","45+"))) -> 35-44
A9: 1065 | B9: 45848 | C9: Pune | D9: Fragrance | E9: Perfume | F9: 32 | G9: Female | H9: 4200 | I9: 3 | J9: Online | K9: Wallet | L9: 5 | M9: =IF(F9<25,"18-24",IF(F9<35,"25-34",IF(F9<45,"35-44","45+"))) -> 25-34
A10: 1114 | B10: 45999 | C10: Bengaluru | D10: Wellness | E10: Vitamin Pack | F10: 41 | G10: Male | H10: 4200 | I10: 2 | J10: Online | K10: Card | L10: 4.9 | M10: =IF(F10<25,"18-24",IF(F10<35,"25-34",IF(F10<45,"35-44","45+"))) -> 35-44
A11: 1099 | B11: 45952 | C11: Mumbai | D11: Wellness | E11: Protein Powder | F11: 36 | G11: Male | H11: 4100 | I11: 2 | J11: Online | K11: UPI | L11: 4.8 | M11: =IF(F11<25,"18-24",IF(F11<35,"25-34",IF(F11<45,"35-44","45+"))) -> 35-44
A12: 1104 | B12: 45969 | C12: Bengaluru | D12: Wellness | E12: Vitamin Pack | F12: 39 | G12: Male | H12: 3950 | I12: 2 | J12: Online | K12: Card | L12: 4.9 | M12: =IF(F12<25,"18-24",IF(F12<35,"25-34",IF(F12<45,"35-44","45+"))) -> 35-44
A13: 1089 | B13: 45922 | C13: Mumbai | D13: Wellness | E13: Protein Powder | F13: 35 | G13: Male | H13: 3900 | I13: 2 | J13: Online | K13: UPI | L13: 4.8 | M13: =IF(F13<25,"18-24",IF(F13<35,"25-34",IF(F13<45,"35-44","45+"))) -> 35-44
... A121: 1046 | B121: 45790 | C121: Chennai | D121: Skincare | E121: Face Wash | F121: 21 | G121: Female | H121: 600 | I121: 1 | J121: Retail Store | K121: Cash | L121: 3.7 | M121: =IF(F121<25,"18-24",IF(F121<35,"25-34",IF(F121<45,"35-44","45+"))) -> 18-24

Sheet EDA
A1: BEAUTY & WELLNESS EXPLORATORY DATA ANALYSIS
A3: Total Sales | B3: =SUM('Cleaned Data'!H:H) -> 278030
A4: Total Quantity | B4: =SUM('Cleaned Data'!I:I) -> 258
A5: Average Sales | B5: =AVERAGE('Cleaned Data'!H:H) -> 2316.9167
A6: Highest Sale | B6: =MAX('Cleaned Data'!H:H) -> 6000
A7: Lowest Sale | B7: =MIN('Cleaned Data'!H:H) -> 600
A8: Total Orders | B8: =COUNTA('Cleaned Data'!A:A)-1 -> 120

Sheet Pivot Tables
A1: Sales by Product Category | D1: Sales by City
A3: Row Labels | B3: Sum of Sales | D3: Row Labels | E3: Sum of Sales
A4: Fragrance | B4: 48050 | D4: Bengaluru | E4: 103950
A5: Haircare | B5: 30910 | D5: Chennai | E5: 9170
A6: Makeup | B6: 58200 | D6: Delhi | E6: 44300
A7: Skincare | B7: 60970 | D7: Hyderabad | E7: 15010
A8: Wellness | B8: 79900 | D8: Mumbai | E8: 57550
A9: Grand Total | B9: 278030 | D9: Pune | E9: 48050
D10: Grand Total | E10: 278030
A13: Sales by Sales Channel | D13: Sales by Gender
A14: Row Labels | B14: Sum of Sales | D14: Row Labels | E14: Sum of Sales
A15: Online | B15: 229610 | D15: Female | E15: 183120
A16: Retail Store | B16: 48420 | D16: Male | E16: 94910
A17: Grand Total | B17: 278030 | D17: Grand Total | E17: 278030

Sheet EDA_2
A1: Sales by Age Group | D1: Monthly Sales Trend
A3: Row Labels | B3: Sum of Sales | D3: Row Labels | E3: Sum of Sales
A4: 18-24 | B4: 16170 | D4: Jan | E4: 14800
A5: 25-34 | B5: 152200 | D5: Feb | E5: 18600
A6: 35-44 | B6: 106260 | D6: Mar | E6: 17980
A7: 45+ | B7: 3400 | D7: Apr | E7: 20850
A8: Grand Total | B8: 278030 | D8: May | E8: 20400
D9: Jun | E9: 20430
D10: Jul | E10: 24080
D11: Aug | E11: 25170
D12: Sep | E12: 26470
D13: Oct | E13: 28050
D14: Nov | E14: 29650
D15: Dec | E15: 31550
D16: Grand Total | E16: 278030

Sheet Sheet9
A1: Sales by Beauty & Wellness Category | J1: Monthly Sales Trend
A20: Sales Distribution by Channel | J20: Sales by City

Sheet Customer Analysis
A2: Row Labels | B2: Sum of Sales | C2: Sum of Order IDA1:J21
A3: 18-24 | B3: 6050 | C3: 3083
A4: 25-34 | B4: 59650 | C4: 22345
A5: 35-44 | B5: 34850 | C5: 11644
A6: 45+ | B6: 3400 | C6: 1064
A7: Grand Total | B7: 103950 | C7: 38136

Sheet Dashboard
A1: BEAUTY & WELLNESS SALES ANALYSIS DASHBOARD
B3: TOTAL SALES | E3: =EDA!B3 -> 278030
B4: TOTAL ORDERS | E4: =EDA!B8 -> 120
B5: AVERAGE SALES | E5: =EDA!B5 -> 2316.9167
B6: HIGHEST SALE | E6: =EDA!B6 -> 6000
B7: LOWEST SALE | E7: =EDA!B7 -> 600
B8: TOTAL QUNTITY | E8: =SUM('Cleaned Data'!I:I) -> 258
A10: BEAUTY & WELLNESS MANAGEMENT DASHBOARD

Sheet Detail1
A1: Details for Sum of Sales - Months (Date): Jan
A3: Order IDA1:J21 | B3: Date | C3: City | D3: Category | E3: Product | F3: Age | G3: Gender | H3: Sales | I3: Quantity | J3: Channel | K3: Payment Mode | L3: Rating | M3: Age Group
A4: 1001 | B4: 45658 | C4: Bengaluru | D4: Skincare | E4: Face Serum | F4: 24 | G4: Female | H4: 1200 | I4: 2 | J4: Online | K4: UPI | L4: 4.5 | M4: 18-24
A5: 1002 | B5: 45660 | C5: Mumbai | D5: Haircare | E5: Shampoo | F5: 31 | G5: Female | H5: 850 | I5: 1 | J5: Retail Store | K5: Card | L5: 4 | M5: 25-34
A6: 1003 | B6: 45662 | C6: Delhi | D6: Makeup | E6: Lipstick | F6: 27 | G6: Female | H6: 1500 | I6: 3 | J6: Online | K6: UPI | L6: 4.7 | M6: 25-34
A7: 1004 | B7: 45665 | C7: Bengaluru | D7: Wellness | E7: Vitamin Pack | F7: 35 | G7: Male | H7: 2200 | I7: 2 | J7: Retail Store | K7: Card | L7: 4.2 | M7: 35-44
A8: 1005 | B8: 45669 | C8: Pune | D8: Fragrance | E8: Perfume | F8: 29 | G8: Female | H8: 1800 | I8: 1 | J8: Online | K8: Wallet | L8: 4.8 | M8: 25-34
A9: 1006 | B9: 45672 | C9: Chennai | D9: Skincare | E9: Face Wash | F9: 22 | G9: Female | H9: 650 | I9: 2 | J9: Online | K9: UPI | L9: 4.1 | M9: 18-24
A10: 1007 | B10: 45675 | C10: Hyderabad | D10: Haircare | E10: Hair Oil | F10: 40 | G10: Male | H10: 900 | I10: 2 | J10: Retail Store | K10: Cash | L10: 3.9 | M10: 35-44
A11: 1008 | B11: 45679 | C11: Bengaluru | D11: Makeup | E11: Foundation | F11: 26 | G11: Female | H11: 2100 | I11: 2 | J11: Online | K11: Card | L11: 4.6 | M11: 25-34
A12: 1009 | B12: 45682 | C12: Mumbai | D12: Wellness | E12: Protein Powder | F12: 33 | G12: Male | H12: 2500 | I12: 1 | J12: Online | K12: UPI | L12: 4.4 | M12: 25-34
A13: 1010 | B13: 45685 | C13: Delhi | D13: Skincare | E13: Moisturizer | F13: 37 | G13: Female | H13: 1100 | I13: 2 | J13: Retail Store | K13: Card | L13: 4.3 | M13: 35-44

Sheet Forecasting
A1: Month | B1: Monthly salary | C1: Sales Change | D1: Percentage Change | F1: Month | G1: Actual Sales | H1: 3-Month Moving Average | I1: Forecast Error | J1: Absolute Error | K1: MAE | L1: Month | M1: Actual Sales | N1: Exponential Smoothing | O1: Forecast Error | P1: Alpha | Q1: Absolute Error | S1: Method | T1: Jan-2026 Forecast | U1: MAE | Y1: Month Number | Z1: Sales | AA1: Slope | AB1: Intercept | AC1: R-Squared | AD1: Regression | AF1: Month | AG1: Actual Sales | AH1: Moving Average | AI1: Exponential Smoothing | AJ1: Regression
A2: Row Labels | B2: Sum of Sales | F2: Jan | G2: 14800 | L2: Jan | M2: 14800 | N2: =M2 -> 14800 | P2: 0.3 | S2: 3-Month Moving Average | T2: 29750 | U2: =K15 -> 3113.0416 | Y2: 1 | Z2: 14800 | AA2: =SLOPE(Z2:Z13,Y2:Y13) -> 1399.4755 | AB2: =INTERCEPT(Z2:Z13,Y2:Y13) -> 14072.576 | AC2: =RSQ(Z2:Z13,Y2:Y13) -> 0.96513278 | AD2: =$AC$2+$AB$2*R2 -> 0.96513278 | AF2: Jan | AG2: 14800 | AI2: =N2 -> 14800 | AJ2: =$AC$2+$AB$2*X2 -> 0.96513278
A3: Jan | B3: 5500 | F3: Feb | G3: 18600 | L3: Feb | M3: 18600 | N3: =$P$2*M2+(1-$P$2)*N2 -> 14800 | O3: =M3-N3 -> 3800 | Q3: =ABS(O3) -> 3800 | S3: Exponential Smoothing | T3: 27819.35 | U3: =Q15 -> 3945.2564 | Y3: 2 | Z3: 18600 | AD3: =$AC$2+$AB$2*R3 -> 0.96513278 | AF3: Feb | AG3: 18600 | AI3: =N3 -> 14800 | AJ3: =$AC$2+$AB$2*X3 -> 0.96513278
A4: Feb | B4: 7500 | C4: =B4-B3 -> 2000 | D4: =(B4-B3)/B3 -> 0.36363636 | F4: Mar | G4: 17980 | L4: Mar | M4: 17980 | N4: =$P$2*M3+(1-$P$2)*N3 -> 15940 | O4: =M4-N4 -> 2040 | Q4: =ABS(O4) -> 2040 | Y4: 3 | Z4: 17980 | AD4: =$AC$2+$AB$2*R4 -> 0.96513278 | AF4: Mar | AG4: 17980 | AI4: =N4 -> 15940 | AJ4: =$AC$2+$AB$2*X4 -> 0.96513278
A5: Mar | B5: 6250 | C5: =B5-B4 -> -1250 | D5: =(B5-B4)/B4 -> -0.16666667 | F5: Apr | G5: 20850 | H5: =AVERAGE(G2:G4) -> 17126.667 | I5: =G5-H5 -> 3723.3333 | J5: =ABS(I5) -> 3723.3333 | K5: =AVERAGE(J5:J13) -> 2817.037 | L5: Apr | M5: 20850 | N5: =$P$2*M4+(1-$P$2)*N4 -> 16552 | O5: =M5-N5 -> 4298 | Q5: =ABS(O5) -> 4298 | Y5: 4 | Z5: 20850 | AD5: =$AC$2+$AB$2*R5 -> 0.96513278 | AF5: Apr | AG5: 20850 | AH5: =AVERAGE(AG2:AG4) -> 17126.667 | AI5: =N5 -> 16552 | AJ5: =$AC$2+$AB$2*X5 -> 0.96513278
A6: Apr | B6: 7900 | C6: =B6-B5 -> 1650 | D6: =(B6-B5)/B5 -> 0.264 | F6: May | G6: 20400 | H6: =AVERAGE(G3:G5) -> 19143.333 | I6: =G6-H6 -> 1256.6667 | J6: =ABS(I6) -> 1256.6667 | K6: =AVERAGE(J6:J14) -> 2703.75 | L6: May | M6: 20400 | N6: =$P$2*M5+(1-$P$2)*N5 -> 17841.4 | O6: =M6-N6 -> 2558.6 | Q6: =ABS(O6) -> 2558.6 | T6: 3-Month Moving Average | Y6: 5 | Z6: 20400 | AD6: =$AC$2+$AB$2*R6 -> 0.96513278 | AF6: May | AG6: 20400 | AH6: =AVERAGE(AG3:AG5) -> 19143.333 | AI6: =$P$2*AH5+(1-$P$2)*AI5 -> 16724.4 | AJ6: =$AC$2+$AB$2*X6 -> 0.96513278
A7: May | B7: 8500 | C7: =B7-B6 -> 600 | D7: =(B7-B6)/B6 -> 0.075949367 | F7: Jun | G7: 20430 | H7: =AVERAGE(G4:G6) -> 19743.333 | I7: =G7-H7 -> 686.66667 | J7: =ABS(I7) -> 686.66667 | K7: =AVERAGE(J7:J15) -> 2910.4762 | L7: Jun | M7: 20430 | N7: =$P$2*M6+(1-$P$2)*N6 -> 18608.98 | O7: =M7-N7 -> 1821.02 | Q7: =ABS(O7) -> 1821.02 | Y7: 6 | Z7: 20430 | AD7: =$AC$2+$AB$2*R7 -> 0.96513278 | AF7: Jun | AG7: 20430 | AH7: =AVERAGE(AG4:AG6) -> 19743.333 | AI7: =$P$2*AH6+(1-$P$2)*AI6 -> 17450.08 | AJ7: =$AC$2+$AB$2*X7 -> 0.96513278
A8: Jun | B8: 7200 | C8: =B8-B7 -> -1300 | D8: =(B8-B7)/B7 -> -0.15294118 | F8: Jul | G8: 24080 | H8: =AVERAGE(G5:G7) -> 20560 | I8: =G8-H8 -> 3520 | J8: =ABS(I8) -> 3520 | K8: =AVERAGE(J8:J16) -> 3281.1111 | L8: Jul | M8: 24080 | N8: =$P$2*M7+(1-$P$2)*N7 -> 19155.286 | O8: =M8-N8 -> 4924.714 | Q8: =ABS(O8) -> 4924.714 | Y8: 7 | Z8: 24080 | AD8: =$AC$2+$AB$2*R8 -> 0.96513278 | AF8: Jul | AG8: 24080 | AH8: =AVERAGE(AG5:AG7) -> 20560 | AI8: =$P$2*AH7+(1-$P$2)*AI7 -> 18138.056 | AJ8: =$AC$2+$AB$2*X8 -> 0.96513278
A9: Jul | B9: 9050 | C9: =B9-B8 -> 1850 | D9: =(B9-B8)/B8 -> 0.25694444 | F9: Aug | G9: 25170 | H9: =AVERAGE(G6:G8) -> 21636.667 | I9: =G9-H9 -> 3533.3333 | J9: =ABS(I9) -> 3533.3333 | K9: =AVERAGE(J9:J17) -> 3233.3333 | L9: Aug | M9: 25170 | N9: =$P$2*M8+(1-$P$2)*N8 -> 20632.7 | O9: =M9-N9 -> 4537.2998 | Q9: =ABS(O9) -> 4537.2998 | Y9: 8 | Z9: 25170 | AD9: =$AC$2+$AB$2*R9 -> 0.96513278 | AF9: Aug | AG9: 25170 | AH9: =AVERAGE(AG6:AG8) -> 21636.667 | AI9: =$P$2*AH8+(1-$P$2)*AI8 -> 18864.639 | AJ9: =$AC$2+$AB$2*X9 -> 0.96513278
A10: Aug | B10: 9250 | C10: =B10-B9 -> 200 | D10: =(B10-B9)/B9 -> 0.022099448 | F10: Sep | G10: 26470 | H10: =AVERAGE(G7:G9) -> 23226.667 | I10: =G10-H10 -> 3243.3333 | J10: =ABS(I10) -> 3243.3333 | K10: =AVERAGE(J10:J18) -> 3158.3333 | L10: Sep | M10: 26470 | N10: =$P$2*M9+(1-$P$2)*N9 -> 21993.89 | O10: =M10-N10 -> 4476.1099 | Q10: =ABS(O10) -> 4476.1099 | Y10: 9 | Z10: 26470 | AD10: =$AC$2+$AB$2*R10 -> 0.96513278 | AF10: Sep | AG10: 26470 | AH10: =AVERAGE(AG7:AG9) -> 23226.667 | AI10: =$P$2*AH9+(1-$P$2)*AI9 -> 19696.247 | AJ10: =$AC$2+$AB$2*X10 -> 0.96513278
A11: Sep | B11: 9850 | C11: =B11-B10 -> 600 | D11: =(B11-B10)/B10 -> 0.064864865 | F11: Oct | G11: 28050 | H11: =AVERAGE(G8:G10) -> 25240 | I11: =G11-H11 -> 2810 | J11: =ABS(I11) -> 2810 | K11: =AVERAGE(J11:J19) -> 3130 | L11: Oct | M11: 28050 | N11: =$P$2*M10+(1-$P$2)*N10 -> 23336.723 | O11: =M11-N11 -> 4713.2769 | Q11: =ABS(O11) -> 4713.2769 | Y11: 10 | Z11: 28050 | AD11: =$AC$2+$AB$2*R11 -> 0.96513278 | AF11: Oct | AG11: 28050 | AH11: =AVERAGE(AG8:AG10) -> 25240 | AI11: =$P$2*AH10+(1-$P$2)*AI10 -> 20755.373 | AJ11: =$AC$2+$AB$2*X11 -> 0.96513278
A12: Oct | B12: 10350 | C12: =B12-B11 -> 500 | D12: =(B12-B11)/B11 -> 0.050761421 | F12: Nov | G12: 29650 | H12: =AVERAGE(G9:G11) -> 26563.333 | I12: =G12-H12 -> 3086.6667 | J12: =ABS(I12) -> 3086.6667 | K12: =AVERAGE(J12:J20) -> 3290 | L12: Nov | M12: 29650 | N12: =$P$2*M11+(1-$P$2)*N11 -> 24750.706 | O12: =M12-N12 -> 4899.2938 | Q12: =ABS(O12) -> 4899.2938 | Y12: 11 | Z12: 29650 | AD12: =$AC$2+$AB$2*R12 -> 0.96513278 | AF12: Nov | AG12: 29650 | AH12: =AVERAGE(AG9:AG11) -> 26563.333 | AI12: =$P$2*AH11+(1-$P$2)*AI11 -> 22100.761 | AJ12: =$AC$2+$AB$2*X12 -> 0.96513278
A13: Nov | B13: 10950 | C13: =B13-B12 -> 600 | D13: =(B13-B12)/B12 -> 0.057971014 | F13: Dec | G13: 31550 | H13: =AVERAGE(G10:G12) -> 28056.667 | I13: =G13-H13 -> 3493.3333 | J13: =ABS(I13) -> 3493.3333 | K13: =AVERAGE(J13:J21) -> 3493.3333 | L13: Dec | M13: 31550 | N13: =$P$2*M12+(1-$P$2)*N12 -> 26220.494 | O13: =M13-N13 -> 5329.5057 | Q13: =ABS(O13) -> 5329.5057 | Y13: 12 | Z13: 31550 | AD13: =$AC$2+$AB$2*R13 -> 0.96513278 | AF13: Dec | AG13: 31550 | AH13: =AVERAGE(AG10:AG12) -> 28056.667 | AI13: =$P$2*AH12+(1-$P$2)*AI12 -> 23439.533 | AJ13: =$AC$2+$AB$2*X13 -> 0.96513278
A14: Dec | B14: 11650 | C14: =B14-B13 -> 700 | D14: =(B14-B13)/B13 -> 0.063926941 | F14: 46023 | H14: =AVERAGE(G11:G13) -> 29750 | L14: 46023 | N14: =$P$2*M13+(1-$P$2)*N13 -> 27819.346 | Y14: 13 | Z14: =$AC$2+$AB$2*Y14 -> 182944.45 | AD14: =$AC$2+$AB$2*R14 -> 0.96513278 | AF14: 46023 | AG14: — | AH14: =AVERAGE(AG11:AG13) -> 29750 | AI14: =$P$2*AH13+(1-$P$2)*AI13 -> 24824.673 | AJ14: =$AC$2+$AB$2*X14 -> 0.96513278
A15: Grand Total | B15: 103950 | K15: =AVERAGE(K5:K13) -> 3113.0416 | P15: MAE | Q15: =AVERAGE(Q3:Q13) -> 3945.2564
A17: Average Monthly Sales | B17: =AVERAGE(B3:B14) -> 8662.5
A18: Highest Monthly Sales | B18: =MAX(B3:B14) -> 11650
A19: Lowest Monthly Sales | B19: =MIN(B3:B14) -> 5500
A20: Highest Sales Month | B20: =INDEX(A3:A14,MATCH(MAX(B3:B14),B3:B14,0)) -> Dec
A21: Lowest Sales Month | B21: =INDEX(A3:A14,MATCH(MIN(B3:B14),B3:B14,0)) -> Jan

Sheet Dashboard Data
A1: KPI | B1: Value | D1: Analysis | E1: Result
A2: Total Sales | B2: =SUM(BeautyData[Sales]) -> 278030 | D2: Highest Sales Product | E2: =INDEX('Product Analysis'!A4:A10,MATCH(MAX('Product Analysis'!B4:B10),'Product Analysis'!B4:B10,0)) -> Grand Total
A3: Total Orders | B3: =COUNTA(BeautyData[Order ID]) -> 120 | D3: Highest Sales City | E3: =INDEX('Pivot Tables'!D4:D9,MATCH(MAX('Pivot Tables'!E4:E9),'Pivot Tables'!E4:E9,0)) -> Bengaluru
A4: Average Order Value | B4: =AVERAGE(BeautyData[Sales]) -> 2316.9167 | D4: Highest Sales Channel | E4: =INDEX('Pivot Tables'!A15:A16,MATCH(MAX('Pivot Tables'!B15:B16),'Pivot Tables'!B15:B16,0)) -> Online
A5: Total Quantity | B5: =SUM(BeautyData[Quantity]) -> 258
A6: Average Rating | B6: =AVERAGE(BeautyData[Rating]) -> 4.5525
A7: Highest Sale | B7: =MAX(BeautyData[Sales]) -> 6000
